sasila/__init__.py
sasila/settings/__init__.py
sasila/settings/default_settings.py
sasila/system_instant/__init__.py
sasila/system_instant/settings.py
sasila/system_instant/blueprints/__init__.py
sasila/system_instant/blueprints/jd.py
sasila/system_instant/crawler/__init__.py
sasila/system_instant/crawler/jd/__init__.py
sasila/system_instant/crawler/jd/request.py
sasila/system_instant/database/__init__.py
sasila/system_instant/database/jd_database.py
sasila/system_instant/manager/__init__.py
sasila/system_instant/manager/jd_manager.py
sasila/system_normal/__init__.py
sasila/system_normal/blueprints/__init__.py
sasila/system_normal/blueprints/slow_spiders.py
sasila/system_normal/database/__init__.py
sasila/system_normal/downloader/__init__.py
sasila/system_normal/downloader/base_downloder.py
sasila/system_normal/downloader/requests_downloader.py
sasila/system_normal/downloader/selenium_downloader.py
sasila/system_normal/downloader/web_driver_pool.py
sasila/system_normal/downloader/http/__init__.py
sasila/system_normal/downloader/http/selenium_response.py
sasila/system_normal/downloader/http/spider_request.py
sasila/system_normal/downloader/http/spider_response.py
sasila/system_normal/downloader/proxy/__init__.py
sasila/system_normal/downloader/proxy/proxy_pool.py
sasila/system_normal/loginer/__init__.py
sasila/system_normal/loginer/base_loginer.py
sasila/system_normal/loginer/jd_loginer.py
sasila/system_normal/manager/__init__.py
sasila/system_normal/manager/spider_manager.py
sasila/system_normal/pipeline/__init__.py
sasila/system_normal/pipeline/base_pipeline.py
sasila/system_normal/pipeline/console_pipeline.py
sasila/system_normal/pipeline/kafa_pipeline.py
sasila/system_normal/pipeline/pic_pipeline.py
sasila/system_normal/pipeline/pipe_item.py
sasila/system_normal/pipeline/test_pipeline.py
sasila/system_normal/pipeline/text_pipeline.py
sasila/system_normal/processor/__init__.py
sasila-0.0.26.dist-info/DESCRIPTION.rst
sasila-0.0.26.dist-info/METADATA
sasila-0.0.26.dist-info/RECORD
sasila-0.0.26.dist-info/WHEEL
sasila-0.0.26.dist-info/metadata.json
sasila-0.0.26.dist-info/top_level.txt
